{"name":"Chewbacca","height":"228","mass":"112","hair_color":"brown","skin_color":"unknown","eye_color":"blue","birth_year":"200BBY","gender":"male","homeworld":"kashyyyk","films":["1","2","3","6","7"],"vehicles":["19"],"starships":["10","22"],"created":"2014-12-10T16:42:45.066000Z","edited":"2014-12-20T21:17:50.332000Z","wiki":"http://starwars.wikia.com/wiki/Chewbacca","image":"https://vignette.wikia.nocookie.net/starwars/images/4/48/Chewbacca_TLJ.png","species":"wookiee","born":-200,"bornLocation":"kashyyyk","id":13}